CHANGES
COPYING
MANIFEST.in
README.md
runtests.py
setup.cfg
setup.py
django_dynamic_preferences_plus.egg-info/PKG-INFO
django_dynamic_preferences_plus.egg-info/SOURCES.txt
django_dynamic_preferences_plus.egg-info/dependency_links.txt
django_dynamic_preferences_plus.egg-info/not-zip-safe
django_dynamic_preferences_plus.egg-info/requires.txt
django_dynamic_preferences_plus.egg-info/top_level.txt
dynamic_preferences/__init__.py
dynamic_preferences/admin.py
dynamic_preferences/fields.py
dynamic_preferences/forms.py
dynamic_preferences/models.py
dynamic_preferences/preferences.py
dynamic_preferences/processors.py
dynamic_preferences/registries.py
dynamic_preferences/serializers.py
dynamic_preferences/settings.py
dynamic_preferences/types.py
dynamic_preferences/urls.py
dynamic_preferences/utils.py
dynamic_preferences/views.py
dynamic_preferences/locale/en/LC_MESSAGES/django.mo
dynamic_preferences/locale/en/LC_MESSAGES/django.po
dynamic_preferences/locale/it/LC_MESSAGES/django.mo
dynamic_preferences/locale/it/LC_MESSAGES/django.po
dynamic_preferences/management/__init__.py
dynamic_preferences/management/commands/__init__.py
dynamic_preferences/management/commands/checkpreferences.py
dynamic_preferences/templates/dynamic_preferences/base.html
dynamic_preferences/templates/dynamic_preferences/form.html
dynamic_preferences/templates/dynamic_preferences/sections.html
dynamic_preferences/templates/dynamic_preferences/testcontext.html
tests/__init__.py
tests/tests.py
tests/types.py
tests/urls.py
tests/test_app/__init__.py
tests/test_app/dynamic_preferences_registry.py