Metadata-Version: 1.1
Name: django-dynamic-preferences-plus
Version: 0.7.13
Summary: A django app for registering dynamic global, site and user preferences
Home-page: https://github.com/mirk8xr/django-dynamic-preferences
Author: Team QWL
Author-email: padova@quag.com
License: BSD
Download-URL: https://github.com/mirk8xr/django-dynamic-preferences/archive/0.7.13.tar.gz
Keywords: django,preferences,admin
Platform: UNKNOWN
Classifier: Environment :: Web Environment
Classifier: Framework :: Django
Classifier: Intended Audience :: Developers
Classifier: License :: OSI Approved :: BSD License
Classifier: Operating System :: OS Independent
Classifier: Programming Language :: Python
Classifier: Programming Language :: Python :: 2.7
Classifier: Topic :: Internet :: WWW/HTTP
Classifier: Topic :: Internet :: WWW/HTTP :: Dynamic Content
